mtv4d/__init__.py
mtv4d/annos_4d/__init__.py
mtv4d/annos_4d/cal_visibility.py
mtv4d/annos_4d/helper.py
mtv4d/annos_4d/misc.py
mtv4d/annos_4d/reusable_4d_functions.py
mtv4d/utils/__init__.py
mtv4d/utils/box_base.py
mtv4d/utils/calib_base.py
mtv4d/utils/camera_base.py
mtv4d/utils/draw_base.py
mtv4d/utils/evaluation_base.py
mtv4d/utils/geo_base.py
mtv4d/utils/io_base.py
mtv4d/utils/load_calib_traj.py
mtv4d/utils/loss_base.py
mtv4d/utils/misc_base.py
mtv4d/utils/o3d_base.py
mtv4d/utils/sensors.py
mtv4d/utils/timestamp_base.py
mtv4d-0.1.15.dist-info/METADATA
mtv4d-0.1.15.dist-info/WHEEL
mtv4d-0.1.15.dist-info/top_level.txt
mtv4d-0.1.15.dist-info/RECORD
