Metadata-Version: 2.2
Name: mtv4d
Version: 0.1.15
Summary: A 4d data sdk
Home-page: https://github.com/ioou/mtv4d
Author: ioou
Author-email: caacabr@163.com
Requires-Dist: numpy
Requires-Dist: scipy
Requires-Dist: tqdm
Requires-Dist: matplotlib
Requires-Dist: pytest
Requires-Dist: pyyaml
Dynamic: author
Dynamic: author-email
Dynamic: description
Dynamic: description-content-type
Dynamic: home-page
Dynamic: requires-dist
Dynamic: summary
